ipping/__init__.py
ipping/__main__.py
ipping/__meta__.py
ipping/protocol.py
ipping/udp.py
ipping-0.2.0.dist-info/LICENSE
ipping-0.2.0.dist-info/METADATA
ipping-0.2.0.dist-info/WHEEL
ipping-0.2.0.dist-info/entry_points.txt
ipping-0.2.0.dist-info/top_level.txt
ipping-0.2.0.dist-info/RECORD
